[
  {
    "Name": "ArcticTech",
    "Game": "csgo",
    "Description": "какая то Арктиктех",
    "GameId": "4465480:csgo",
    "DownloadUrl": "https://github.com/mellstroed/neverpuzo/releases/download/arctictech/ArcticTech.zip",
    "FileName": "customflow.zip",
    "ExePath": "injector.exe",
    "IconUrl": "https://raw.githubusercontent.com/mellstroed/neverpuzo/main/png/arctictech.png"
  },
  {
    "Name": "customflow",
    "Game": "csgo",
    "Description": "переделка airflow",
    "GameId": "4465480:csgo",
    "DownloadUrl": "https://github.com/mellstroed/neverpuzo/releases/download/customflow/customflow.zip",
    "FileName": "customflow.zip",
    "ExePath": "injector.exe",
    "IconUrl": "https://raw.githubusercontent.com/mellstroed/neverpuzo/main/png/airflow.png"
  },
  {
    "Name": "aimware",
    "Game": "csgo",
    "Description": "хуйня под кс2 но раньше под ксго в 2019 был норм",
    "GameId": "4465480:csgo",
    "DownloadUrl": "https://github.com/mellstroed/neverpuzo/releases/download/aimware/aimware.zip",
    "FileName": "aimware.zip",
    "ExePath": "injector.exe",
    "IconUrl": "https://raw.githubusercontent.com/mellstroed/neverpuzo/main/png/aimware.png"
  },
  {
    "Name": "kamidere",
    "Game": "csgo",
    "Description": "Крутой мувмент чит",
    "GameId": "4465480:csgo",
    "DownloadUrl": "https://github.com/mellstroed/neverpuzo/releases/download/Kamidere/kamidere.zip",
    "FileName": "kamidere.zip",
    "ExePath": "injector.exe",
    "IconUrl": "https://raw.githubusercontent.com/mellstroed/neverpuzo/main/png/kamidere.png"
  },
  {
    "Name": "neverlose",
    "Game": "csgo",
    "GameId": "4465480:csgo",
    "Description": "Крутая синяя паста которая миссает постоянно в correction",
    "DownloadUrl": "https://github.com/mellstroed/neverpuzo/releases/download/neverlose/123.1.zip",
    "FileName": "123.1.zip",
    "ExePath": "neverlose-server.exe",
    "IconUrl": "https://raw.githubusercontent.com/mellstroed/neverpuzo/main/png/neverlose.png",
    "Type": "neverlose"
  },
  {
    "Name": "ev0lve",
    "Game": "csgo",
    "GameId": "4465480:csgo",
    "Description": "Премиум чит для CS:GO с мощными рейдж функциями",
    "DownloadUrl": "https://github.com/mellstroed/neverpuzo/releases/download/ev0/ev0.zip",
    "FileName": "ev0.zip",
    "ExePath": "injector.exe",
    "IconUrl": "https://raw.githubusercontent.com/mellstroed/neverpuzo/main/png/ev0.png"
  },
  {
    "Name": "primordial",
    "Game": "csgo",
    "GameId": "4465480:csgo",
    "Description": "Красивый чит с красивыми визуалами",
    "DownloadUrl": "https://github.com/mellstroed/neverpuzo/releases/download/primordial/prim.zip",
    "FileName": "prim.zip",
    "ExePath": "injector.exe",
    "IconUrl": "https://raw.githubusercontent.com/mellstroed/neverpuzo/main/png/prim.png"
  },
  {
    "Name": "legendware",
    "Game": "csgo",
    "GameId": "4465480:csgo",
    "Description": "Паста с функциями от лидосира",
    "DownloadUrl": "https://github.com/mellstroed/neverpuzo/releases/download/legendware/lw.zip",
    "FileName": "lw.zip",
    "ExePath": "injector.exe",
    "IconUrl": "https://raw.githubusercontent.com/mellstroed/neverpuzo/main/png/lw.png"
  },
  {
    "Name": "gamesense",
    "Game": "csgo",
    "GameId": "4465480:csgo",
    "Description": "зеленая паста и инвайты по 40к$",
    "DownloadUrl": "https://github.com/mellstroed/neverpuzo/releases/download/gamesense/gs.zip",
    "FileName": "gs.zip",
    "ExePath": "injector.exe",
    "IconUrl": "https://raw.githubusercontent.com/mellstroed/neverpuzo/main/png/gs.png"
  },
  {
    "Name": "onetap",
    "Game": "csgo",
    "GameId": "4465480:csgo",
    "Description": "Воньтап в3",
    "DownloadUrl": "https://github.com/mellstroed/neverpuzo/releases/download/onetap/ot.zip",
    "FileName": "ot.zip",
    "ExePath": "injector.exe",
    "IconUrl": "https://raw.githubusercontent.com/mellstroed/neverpuzo/main/png/ot.png"
  },

  {
    "Name": "fatality (siniy)",
    "Game": "csgo",
    "GameId": "4465480:csgo",
    "Description": "синяя паста фаталити",
    "DownloadUrl": "https://github.com/mellstroed/neverpuzo/releases/download/fatalitysiniy/ft.zip",
    "FileName": "ft.zip",
    "ExePath": "injector.exe",
    "IconUrl": "https://raw.githubusercontent.com/mellstroed/neverpuzo/main/png/ft.png"
  },
  {
    "Name": "bob",
    "Game": "csgo",
    "GameId": "4465480:csgo",
    "Description": "просто добавьте ске к началу",
    "DownloadUrl": "https://github.com/mellstroed/neverpuzo/releases/download/bob/bob.zip",
    "FileName": "bob.zip",
    "ExePath": "injector.exe",
    "IconUrl": "https://raw.githubusercontent.com/mellstroed/neverpuzo/main/png/bob.png"
  },
  {
    "Name": "FURRYWARE",
    "Game": "csgo",
    "GameId": "4465480:csgo",
    "Description": "фурятина",
    "DownloadUrl": "https://github.com/mellstroed/neverpuzo/releases/download/furryware/furryware.zip",
    "FileName": "furryware.zip",
    "ExePath": "injector.exe",
    "IconUrl": "https://raw.githubusercontent.com/mellstroed/neverpuzo/main/png/furryware.png"
  },
  {
    "Name": "Havoc",
    "Game": "csgo",
    "GameId": "4465480:csgo",
    "Description": "паста геймсенса",
    "DownloadUrl": "https://github.com/mellstroed/neverpuzo/releases/download/havoc/havoc.zip",
    "FileName": "havoc.zip",
    "ExePath": "injector.exe",
    "IconUrl": "https://raw.githubusercontent.com/mellstroed/neverpuzo/main/png/havoc.png"
  },
  {
    "Name": "sosality",
    "Game": "csgo",
    "GameId": "4465480:csgo",
    "Description": "крутая фиолетовая паста фаталити",
    "DownloadUrl": "https://github.com/mellstroed/neverpuzo/releases/download/sosality/sosality.zip",
    "FileName": "sosality.zip",
    "ExePath": "injector.exe",
    "IconUrl": "https://raw.githubusercontent.com/mellstroed/neverpuzo/main/png/sosality.png"
  },
  {
    "Name": "vivo 2.5",
    "Game": "csgo",
    "GameId": "4465480:csgo",
    "Description": "виво х500 про, хорошая паста легендвара",
    "DownloadUrl": "https://github.com/mellstroed/neverpuzo/releases/download/Vivo/vivo.zip",
    "FileName": "vivo.zip",
    "ExePath": "injector.exe",
    "IconUrl": "https://raw.githubusercontent.com/mellstroed/neverpuzo/main/png/vivo.png"
  },
  {
    "Name": "spermaware",
    "Game": "csgo",
    "GameId": "4465480:csgo",
    "Description": "паста рейза ( ратера )",
    "DownloadUrl": "https://github.com/mellstroed/neverpuzo/releases/download/spermaware/spermaware.zip",
    "FileName": "spermaware.zip",
    "ExePath": "injector.exe",
    "IconUrl": "https://raw.githubusercontent.com/mellstroed/neverpuzo/main/png/spermaware.png"
  },
  {
    "Name": "naval",
    "Game": "csgo",
    "GameId": "4465480:csgo",
    "Description": "навальный сидит",
    "DownloadUrl": "https://github.com/mellstroed/neverpuzo/releases/download/naval/naval.zip",
    "FileName": "naval.zip",
    "ExePath": "injector.exe",
    "IconUrl": "https://raw.githubusercontent.com/mellstroed/neverpuzo/main/png/naval.png"
  }
]
